partuv/__init__.py
partuv/_core.cpython-311-x86_64-linux-gnu.so
partuv/preprocess.py
partuv/.libs/libeasy_profiler.so
partuv/preprocess_utils/PartField_pipeline.py
partuv/preprocess_utils/__init__.py
partuv/preprocess_utils/manifold.py
partuv/preprocess_utils/merge_V_obj.py
partuv/preprocess_utils/partfield/AgglomerativeClustering.py
partuv/preprocess_utils/partfield/__init__.py
partuv/preprocess_utils/partfield/run_PF.py
partuv/preprocess_utils/partfield/config/partfield.yaml
partuv/preprocess_utils/partfield/partfield/model_trainer_pvcnn.py
partuv/preprocess_utils/partfield/partfield/config/__init__.py
partuv/preprocess_utils/partfield/partfield/config/defaults.py
partuv/preprocess_utils/partfield/partfield/model/model_utils.py
partuv/preprocess_utils/partfield/partfield/model/triplane.py
partuv/preprocess_utils/partfield/partfield/model/PVCNN/conv_pointnet.py
partuv/preprocess_utils/partfield/partfield/model/PVCNN/dnnlib_util.py
partuv/preprocess_utils/partfield/partfield/model/PVCNN/encoder_pc.py
partuv/preprocess_utils/partfield/partfield/model/PVCNN/pc_encoder.py
partuv/preprocess_utils/partfield/partfield/model/PVCNN/unet_3daware.py
partuv/preprocess_utils/partfield/partfield/model/PVCNN/pv_module/__init__.py
partuv/preprocess_utils/partfield/partfield/model/PVCNN/pv_module/ball_query.py
partuv/preprocess_utils/partfield/partfield/model/PVCNN/pv_module/frustum.py
partuv/preprocess_utils/partfield/partfield/model/PVCNN/pv_module/loss.py
partuv/preprocess_utils/partfield/partfield/model/PVCNN/pv_module/pointnet.py
partuv/preprocess_utils/partfield/partfield/model/PVCNN/pv_module/pvconv.py
partuv/preprocess_utils/partfield/partfield/model/PVCNN/pv_module/se.py
partuv/preprocess_utils/partfield/partfield/model/PVCNN/pv_module/shared_mlp.py
partuv/preprocess_utils/partfield/partfield/model/PVCNN/pv_module/voxelization.py
partuv/preprocess_utils/partfield/partfield/model/PVCNN/pv_module/functional/__init__.py
partuv-0.1.1.dist-info/METADATA
partuv-0.1.1.dist-info/WHEEL
partuv-0.1.1.dist-info/RECORD
