Metadata-Version: 2.2
Name: partuv
Version: 0.1.1
Summary: UV unwrapping pipeline with pybind11 bindings and preprocessing utilities
Author: Your Name
Requires-Python: >=3.9
Requires-Dist: numpy
Requires-Dist: trimesh
Requires-Dist: scipy
Requires-Dist: opencv-python
